eurlxp/__init__.py
eurlxp/cli.py
eurlxp/client.py
eurlxp/models.py
eurlxp/parser.py
eurlxp/py.typed
eurlxp/sparql.py
eurlxp-0.3.3.dist-info/WHEEL
eurlxp-0.3.3.dist-info/entry_points.txt
eurlxp-0.3.3.dist-info/METADATA
eurlxp-0.3.3.dist-info/RECORD
