Metadata-Version: 2.3
Name: eurlxp
Version: 0.3.3
Summary: A modern EUR-Lex parser for Python - fetch and parse EU legal documents
Keywords: eurlex,eu,legal,parser,regulations,directives,celex
Author: Moritz Schlichting
Author-email: Moritz Schlichting <moritz@info.nl>
License: MIT
Classifier: Development Status :: 4 - Beta
Classifier: Intended Audience :: Developers
Classifier: Intended Audience :: Legal Industry
Classifier: License :: OSI Approved :: MIT License
Classifier: Operating System :: OS Independent
Classifier: Programming Language :: Python :: 3
Classifier: Programming Language :: Python :: 3.10
Classifier: Programming Language :: Python :: 3.11
Classifier: Programming Language :: Python :: 3.12
Classifier: Programming Language :: Python :: 3.13
Classifier: Programming Language :: Python :: 3.14
Classifier: Topic :: Text Processing :: Markup :: HTML
Classifier: Topic :: Text Processing :: Markup :: XML
Classifier: Typing :: Typed
Requires-Dist: httpx>=0.27.0
Requires-Dist: beautifulsoup4>=4.12.0
Requires-Dist: lxml>=5.0.0
Requires-Dist: pydantic>=2.0.0
Requires-Dist: pandas>=2.0.0
Requires-Dist: typer>=0.12.0
Requires-Dist: rich>=13.0.0
Requires-Dist: pymupdf>=1.24.0
Requires-Dist: eurlxp[sparql,dev] ; extra == 'all'
Requires-Dist: pytest>=8.0.0 ; extra == 'dev'
Requires-Dist: pytest-cov>=4.0.0 ; extra == 'dev'
Requires-Dist: pytest-asyncio>=0.23.0 ; extra == 'dev'
Requires-Dist: ruff>=0.4.0 ; extra == 'dev'
Requires-Dist: pyright>=1.1.0 ; extra == 'dev'
Requires-Dist: pre-commit>=3.0.0 ; extra == 'dev'
Requires-Dist: sparqlwrapper>=2.0.0 ; extra == 'sparql'
Requires-Dist: rdflib>=7.0.0 ; extra == 'sparql'
Maintainer: Moritz Schlichting
Maintainer-email: Moritz Schlichting <moritz@info.nl>
Requires-Python: >=3.10
Project-URL: Changelog, https://github.com/morrieinmaas/eurlxp/blob/main/CHANGELOG.md
Project-URL: Documentation, https://github.com/morrieinmaas/eurlxp#readme
Project-URL: Homepage, https://github.com/morrieinmaas/eurlxp
Project-URL: Issues, https://github.com/morrieinmaas/eurlxp/issues
Project-URL: Repository, https://github.com/morrieinmaas/eurlxp.git
Provides-Extra: all
Provides-Extra: dev
Provides-Extra: sparql
